aumtest/__init__.py
aumtest/aumtest_runner.py
aumtest/driver.py
aumtest/project.py
aumtest/version.py
aumtest/common/__init__.py
aumtest/common/check.py
aumtest/common/decorator.py
aumtest/common/dict.py
aumtest/common/log.py
aumtest/common/variable_global.py
aumtest/drivers/__init__.py
aumtest/drivers/driver.py
aumtest/drivers/driver_base_app.py
aumtest/drivers/driver_base_web.py
aumtest/drivers/appium/__init__.py
aumtest/drivers/appium/driver_appium.py
aumtest/drivers/macaca/__init__.py
aumtest/drivers/macaca/driver_macaca.py
aumtest/keywords/__init__.py
aumtest/keywords/keywords.py
aumtest/keywords/minium_keywords.py
aumtest/result/__init__.py
aumtest/result/html_result.py
aumtest/result/test_result.py
aumtest/result/test_runner.py
aumtest/runner/__init__.py
aumtest/runner/action_analysis.py
aumtest/runner/action_executor_app.py
aumtest/runner/action_executor_base.py
aumtest/runner/action_executor_minium.py
aumtest/runner/action_executor_web.py
aumtest/runner/case_analysis.py
aumtest/runner/run_case.py
aumtest/runner/test_case.py
aumtest/utils/__init__.py
aumtest/utils/devices_utils.py
aumtest/utils/opcv_utils.py
aumtest/utils/server_utils_app.py
aumtest/utils/server_utils_web.py
aumtest/utils/testcast_utils.py
aumtest/utils/yaml_utils.py
aumtest-3.0.0.dist-info/METADATA
aumtest-3.0.0.dist-info/WHEEL
aumtest-3.0.0.dist-info/entry_points.txt
aumtest-3.0.0.dist-info/top_level.txt
aumtest-3.0.0.dist-info/RECORD
