Metadata-Version: 2.1
Name: aumtest
Version: 3.0.0
Summary: UNKNOWN
Home-page: UNKNOWN
License: UNKNOWN
Platform: UNKNOWN
Requires-Python: >=3.8.0
Requires-Dist: PyYAML (>=5.1.2)
Requires-Dist: wd (>=1.0.1)
Requires-Dist: selenium
Requires-Dist: colorama
